pytodotxt/__init__.py
pytodotxt/task.py
pytodotxt/todotxt.py
pytodotxt-3.0.0.dist-info/licenses/AUTHORS.md
pytodotxt-3.0.0.dist-info/licenses/LICENSE
pytodotxt-3.0.0.dist-info/METADATA
pytodotxt-3.0.0.dist-info/WHEEL
pytodotxt-3.0.0.dist-info/top_level.txt
pytodotxt-3.0.0.dist-info/RECORD
