Metadata-Version: 2.4
Name: pytodotxt
Version: 3.0.0
Summary: Library to access todo.txt-like task lists
Author-email: R <contact+pytodotxt@vonshednob.cc>
License-Expression: MIT
Project-URL: Repository, https://vonshednob.cc/pytodotxt
Project-URL: Issues, https://codeberg.org/vonshednob/pytodotxt/issues
Keywords: todotxt
Classifier: Development Status :: 5 - Production/Stable
Classifier: Intended Audience :: Developers
Classifier: Programming Language :: Python :: 3
Requires-Python: >=3.7
License-File: LICENSE
License-File: AUTHORS.md
Dynamic: license-file
